{
  "table_id": {
    "value": "FGJ",
    "rot13": false
  },
  "table_sh146_name": {
    "value": "o0-time",
    "rot13": true
  },
  "fixed_parameters": [
    {
      "name": "txtSearch",
      "value": ""
    },
    {
      "name": "cboGeograph",
      "value": "All"
    },
    {
      "name": "btnDownload",
      "value": "Download"
    }
  ],
  "user_parameters": [
    {
      "name": "cboYear",
      "type": "year"
    },
    {
      "name": "cboPeriod",
      "type": "numberic_month"
    }
  ],
  "primary_key": ["FlightDate", "TailNumber", "ActualDepartureTime"],
  "columns": [
    {
      "name": "Year",
      "payload_name": "YEAR",
      "response_name": "YEAR",
      "has_lookup": false
    },
    {
      "name": "Quarter",
      "payload_name": "QUARTER",
      "response_name": "QUARTER",
      "has_lookup": false
    },
    {
      "name": "Month",
      "payload_name": "MONTH",
      "response_name": "MONTH",
      "has_lookup": true,
      "lookup": "months"
    },
    {
      "name": "DayofMonth",
      "payload_name": "DAY_OF_MONTH",
      "response_name": "DAY_OF_MONTH",
      "has_lookup": false
    },
    {
      "name": "DayOfWeek",
      "payload_name": "DAY_OF_WEEK",
      "response_name": "DAY_OF_WEEK",
      "has_lookup": true,
      "lookup": "day_of_week"
    },
    {
      "name": "FlightDate",
      "payload_name": "FL_DATE",
      "response_name": "FL_DATE",
      "has_lookup": false
    },
    {
      "name": "ReportingAirline",
      "payload_name": "OP_UNIQUE_CARRIER",
      "response_name": "OP_UNIQUE_CARRIER",
      "has_lookup": true,
      "lookup": "aviation.unique_carriers"
    },
    {
      "name": "DOT_ID_ReportingAirline",
      "payload_name": "OP_CARRIER_AIRLINE_ID",
      "response_name": "OP_CARRIER_AIRLINE_ID",
      "has_lookup": true,
      "lookup": "aviation.airline_id"
    },
    {
      "name": "IATA_CODE_ReportingAirline",
      "payload_name": "OP_CARRIER",
      "response_name": "OP_CARRIER",
      "has_lookup": true,
      "lookup": "aviation.carrier_history"
    },
    {
      "name": "TailNumber",
      "payload_name": "TAIL_NUM",
      "response_name": "TAIL_NUM",
      "has_lookup": false
    },
    {
      "name": "ReportingAirlineFlightNumber",
      "payload_name": "OP_CARRIER_FL_NUM",
      "response_name": "OP_CARRIER_FL_NUM",
      "has_lookup": false
    },
    {
      "name": "OriginAirportID",
      "payload_name": "ORIGIN_AIRPORT_ID",
      "response_name": "ORIGIN_AIRPORT_ID",
      "has_lookup": true,
      "lookup": "aviation.airport_id"
    },
    {
      "name": "OriginAirportSeqID",
      "payload_name": "ORIGIN_AIRPORT_SEQ_ID",
      "response_name": "ORIGIN_AIRPORT_SEQ_ID",
      "has_lookup": true,
      "lookup": "aviation.airport_seq_id"
    },
    {
      "name": "OriginCityMarketID",
      "payload_name": "ORIGIN_CITY_MARKET_ID",
      "response_name": "ORIGIN_CITY_MARKET_ID",
      "has_lookup": true,
      "lookup": "aviation.city_market_id"
    },
    {
      "name": "OriginAirport",
      "payload_name": "ORIGIN",
      "response_name": "ORIGIN",
      "has_lookup": true,
      "lookup": "aviation.airport"
    },
    {
      "name": "OriginCityName",
      "payload_name": "ORIGIN_CITY_NAME",
      "response_name": "ORIGIN_CITY_NAME",
      "has_lookup": false
    },
    {
      "name": "OriginState",
      "payload_name": "ORIGIN_STATE_ABR",
      "response_name": "ORIGIN_STATE_ABR",
      "has_lookup": true,
      "lookup": "aviation.airport_state_abr"
    },
    {
      "name": "OriginStateFips",
      "payload_name": "ORIGIN_STATE_FIPS",
      "response_name": "ORIGIN_STATE_FIPS",
      "has_lookup": true,
      "lookup": "aviation.state_fips"
    },
    {
      "name": "OriginStateName",
      "payload_name": "ORIGIN_STATE_NM",
      "response_name": "ORIGIN_STATE_NM",
      "has_lookup": false
    },
    {
      "name": "OriginWac",
      "payload_name": "ORIGIN_WAC",
      "response_name": "ORIGIN_WAC",
      "has_lookup": true,
      "lookup": "aviation.world_area_code"
    },
    {
      "name": "DestinationAirportID",
      "payload_name": "DEST_AIRPORT_ID",
      "response_name": "DEST_AIRPORT_ID",
      "has_lookup": true,
      "lookup": "aviation.airport_id"
    },
    {
      "name": "DestinationAirportSeqID",
      "payload_name": "DEST_AIRPORT_SEQ_ID",
      "response_name": "DEST_AIRPORT_SEQ_ID",
      "has_lookup": true,
      "lookup": "aviation.airport_seq_id"
    },
    {
      "name": "DestinationCityMarketID",
      "payload_name": "DEST_CITY_MARKET_ID",
      "response_name": "DEST_CITY_MARKET_ID",
      "has_lookup": true,
      "lookup": "aviation.city_market_id"
    },
    {
      "name": "DestinationAirport",
      "payload_name": "DEST",
      "response_name": "DEST",
      "has_lookup": true,
      "lookup": "aviation.airport"
    },
    {
      "name": "DestinationCityName",
      "payload_name": "DEST_CITY_NAME",
      "response_name": "DEST_CITY_NAME",
      "has_lookup": false
    },
    {
      "name": "DestinationState",
      "payload_name": "DEST_STATE_ABR",
      "response_name": "DEST_STATE_ABR",
      "has_lookup": true,
      "lookup": "aviation.airport_state_abr"
    },
    {
      "name": "DestinationStateFips",
      "payload_name": "DEST_STATE_FIPS",
      "response_name": "DEST_STATE_FIPS",
      "has_lookup": true,
      "lookup": "aviation.state_fips"
    },
    {
      "name": "DestinationStateName",
      "payload_name": "DEST_STATE_NM",
      "response_name": "DEST_STATE_NM",
      "has_lookup": false
    },
    {
      "name": "DestinationWac",
      "payload_name": "DEST_WAC",
      "response_name": "DEST_WAC",
      "has_lookup": true,
      "lookup": "aviation.world_area_code"
    },
    {
      "name": "ScheduledDepartureTime",
      "payload_name": "CRS_DEP_TIME",
      "response_name": "CRS_DEP_TIME",
      "has_lookup": false
    },
    {
      "name": "ActualDepartureTime",
      "payload_name": "DEP_TIME",
      "response_name": "DEP_TIME",
      "has_lookup": false
    },
    {
      "name": "DepartureDelay",
      "payload_name": "DEP_DELAY",
      "response_name": "DEP_DELAY",
      "has_lookup": false
    },
    {
      "name": "DepartureDelayMinutes",
      "payload_name": "DEP_DELAY_NEW",
      "response_name": "DEP_DELAY_NEW",
      "has_lookup": false
    },
    {
      "name": "DepartureDelay15",
      "payload_name": "DEP_DEL15",
      "response_name": "DEP_DEL15",
      "has_lookup": false
    },
    {
      "name": "DepartureDelayGroups",
      "payload_name": "DEP_DELAY_GROUP",
      "response_name": "DEP_DELAY_GROUP",
      "has_lookup": true,
      "lookup": "aviation.airline_otp.delay_groups"
    },
    {
      "name": "DepartureTimeBlock",
      "payload_name": "DEP_TIME_BLK",
      "response_name": "DEP_TIME_BLK",
      "has_lookup": true,
      "lookup": "aviation.airline_otp.departure_time_block"
    },
    {
      "name": "TaxiOut",
      "payload_name": "TAXI_OUT",
      "response_name": "TAXI_OUT",
      "has_lookup": false
    },
    {
      "name": "WheelsOff",
      "payload_name": "WHEELS_OFF",
      "response_name": "WHEELS_OFF",
      "has_lookup": false
    },
    {
      "name": "WheelsOn",
      "payload_name": "WHEELS_ON",
      "response_name": "WHEELS_ON",
      "has_lookup": false
    },
    {
      "name": "TaxiIn",
      "payload_name": "TAXI_IN",
      "response_name": "TAXI_IN",
      "has_lookup": false
    },
    {
      "name": "ScheduledArrivalTime",
      "payload_name": "CRS_ARR_TIME",
      "response_name": "CRS_ARR_TIME",
      "has_lookup": false
    },
    {
      "name": "ActualArrivalTime",
      "payload_name": "ARR_TIME",
      "response_name": "ARR_TIME",
      "has_lookup": false
    },
    {
      "name": "ArrivalDelay",
      "payload_name": "ARR_DELAY",
      "response_name": "ARR_DELAY",
      "has_lookup": false
    },
    {
      "name": "ArrivalDelayMinutes",
      "payload_name": "ARR_DELAY_NEW",
      "response_name": "ARR_DELAY_NEW",
      "has_lookup": false
    },
    {
      "name": "ArrivalDelay15",
      "payload_name": "ARR_DEL15",
      "response_name": "ARR_DEL15",
      "has_lookup": false
    },
    {
      "name": "ArrivalDelayGroups",
      "payload_name": "ARR_DELAY_GROUP",
      "response_name": "ARR_DELAY_GROUP",
      "has_lookup": true,
      "lookup": "aviation.airline_otp.delay_groups"
    },
    {
      "name": "ArrivalTimeBlock",
      "payload_name": "ARR_TIME_BLK",
      "response_name": "ARR_TIME_BLK",
      "has_lookup": true,
      "lookup": "aviation.airline_otp.departure_time_block"
    },
    {
      "name": "Cancelled",
      "payload_name": "CANCELLED",
      "response_name": "CANCELLED",
      "has_lookup": false
    },
    {
      "name": "CancellationCode",
      "payload_name": "CANCELLATION_CODE",
      "response_name": "CANCELLATION_CODE",
      "has_lookup": true,
      "lookup": "aviation.airline_otp.cancelation_codes"
    },
    {
      "name": "Diverted",
      "payload_name": "DIVERTED",
      "response_name": "DIVERTED",
      "has_lookup": false
    },
    {
      "name": "ScheduledElapsedTime",
      "payload_name": "CRS_ELAPSED_TIME",
      "response_name": "CRS_ELAPSED_TIME",
      "has_lookup": false
    },
    {
      "name": "ActualElapsedTime",
      "payload_name": "ACTUAL_ELAPSED_TIME",
      "response_name": "ACTUAL_ELAPSED_TIME",
      "has_lookup": false
    },
    {
      "name": "AirTime",
      "payload_name": "AIR_TIME",
      "response_name": "AIR_TIME",
      "has_lookup": false
    },
    {
      "name": "Flights",
      "payload_name": "FLIGHTS",
      "response_name": "FLIGHTS",
      "has_lookup": false
    },
    {
      "name": "Distance",
      "payload_name": "DISTANCE",
      "response_name": "DISTANCE",
      "has_lookup": false
    },
    {
      "name": "DistanceGroup",
      "payload_name": "DISTANCE_GROUP",
      "response_name": "DISTANCE_GROUP",
      "has_lookup": true,
      "lookup": "aviation.airline_otp.distance_group"
    },
    {
      "name": "CarrierDelay",
      "payload_name": "CARRIER_DELAY",
      "response_name": "CARRIER_DELAY",
      "has_lookup": false
    },
    {
      "name": "WeatherDelay",
      "payload_name": "WEATHER_DELAY",
      "response_name": "WEATHER_DELAY",
      "has_lookup": false
    },
    {
      "name": "NASDelay",
      "payload_name": "NAS_DELAY",
      "response_name": "NAS_DELAY",
      "has_lookup": false
    },
    {
      "name": "SecurityDelay",
      "payload_name": "SECURITY_DELAY",
      "response_name": "SECURITY_DELAY",
      "has_lookup": false
    },
    {
      "name": "LateAircraftDelay",
      "payload_name": "LATE_AIRCRAFT_DELAY",
      "response_name": "LATE_AIRCRAFT_DELAY",
      "has_lookup": false
    },
    {
      "name": "FirstDepartureTime",
      "payload_name": "FIRST_DEP_TIME",
      "response_name": "FIRST_DEP_TIME",
      "has_lookup": false
    },
    {
      "name": "TotalAddGroundTime",
      "payload_name": "TOTAL_ADD_GTIME",
      "response_name": "TOTAL_ADD_GTIME",
      "has_lookup": false
    },
    {
      "name": "LongestAddGroundTime",
      "payload_name": "LONGEST_ADD_GTIME",
      "response_name": "LONGEST_ADD_GTIME",
      "has_lookup": false
    },
    {
      "name": "DivertedAirportLandings",
      "payload_name": "DIV_AIRPORT_LANDINGS",
      "response_name": "DIV_AIRPORT_LANDINGS",
      "has_lookup": true,
      "lookup": "aviation.airline_otp.diverted_landings"
    },
    {
      "name": "DivertedReachedDestination",
      "payload_name": "DIV_REACHED_DEST",
      "response_name": "DIV_REACHED_DEST",
      "has_lookup": false
    },
    {
      "name": "DivertedActualElapsedTime",
      "payload_name": "DIV_ACTUAL_ELAPSED_TIME",
      "response_name": "DIV_ACTUAL_ELAPSED_TIME",
      "has_lookup": false
    },
    {
      "name": "DivertedArrivalDelay",
      "payload_name": "DIV_ARR_DELAY",
      "response_name": "DIV_ARR_DELAY",
      "has_lookup": false
    },
    {
      "name": "DivertedDistance",
      "payload_name": "DIV_DISTANCE",
      "response_name": "DIV_DISTANCE",
      "has_lookup": false
    },
    {
      "name": "Diverted1Airport",
      "payload_name": "DIV1_AIRPORT",
      "response_name": "DIV1_AIRPORT",
      "has_lookup": false
    },
    {
      "name": "Diverted1AirportID",
      "payload_name": "DIV1_AIRPORT_ID",
      "response_name": "DIV1_AIRPORT_ID",
      "has_lookup": true,
      "lookup": "aviation.airport_id"
    },
    {
      "name": "Diverted1AirportSeqID",
      "payload_name": "DIV1_AIRPORT_SEQ_ID",
      "response_name": "DIV1_AIRPORT_SEQ_ID",
      "has_lookup": true,
      "lookup": "aviation.airport_seq_id"
    },
    {
      "name": "Diverted1WheelsOn",
      "payload_name": "DIV1_WHEELS_ON",
      "response_name": "DIV1_WHEELS_ON",
      "has_lookup": false
    },
    {
      "name": "Diverted1TotalGroundTime",
      "payload_name": "DIV1_TOTAL_GTIME",
      "response_name": "DIV1_TOTAL_GTIME",
      "has_lookup": false
    },
    {
      "name": "Diverted1LongestGroundTime",
      "payload_name": "DIV1_LONGEST_GTIME",
      "response_name": "DIV1_LONGEST_GTIME",
      "has_lookup": false
    },
    {
      "name": "Diverted1WheelsOff",
      "payload_name": "DIV1_WHEELS_OFF",
      "response_name": "DIV1_WHEELS_OFF",
      "has_lookup": false
    },
    {
      "name": "Diverted1TailNum",
      "payload_name": "DIV1_TAIL_NUM",
      "response_name": "DIV1_TAIL_NUM",
      "has_lookup": false
    },
    {
      "name": "Diverted2Airport",
      "payload_name": "DIV2_AIRPORT",
      "response_name": "DIV2_AIRPORT",
      "has_lookup": false
    },
    {
      "name": "Diverted2AirportID",
      "payload_name": "DIV2_AIRPORT_ID",
      "response_name": "DIV2_AIRPORT_ID",
      "has_lookup": true,
      "lookup": "aviation.airport_id"
    },
    {
      "name": "Diverted2AirportSeqID",
      "payload_name": "DIV2_AIRPORT_SEQ_ID",
      "response_name": "DIV2_AIRPORT_SEQ_ID",
      "has_lookup": true,
      "lookup": "aviation.airport_seq_id"
    },
    {
      "name": "Diverted2WheelsOn",
      "payload_name": "DIV2_WHEELS_ON",
      "response_name": "DIV2_WHEELS_ON",
      "has_lookup": false
    },
    {
      "name": "Diverted2TotalGroundTime",
      "payload_name": "DIV2_TOTAL_GTIME",
      "response_name": "DIV2_TOTAL_GTIME",
      "has_lookup": false
    },
    {
      "name": "Diverted2LongestGroundTime",
      "payload_name": "DIV2_LONGEST_GTIME",
      "response_name": "DIV2_LONGEST_GTIME",
      "has_lookup": false
    },
    {
      "name": "Diverted2WheelsOff",
      "payload_name": "DIV2_WHEELS_OFF",
      "response_name": "DIV2_WHEELS_OFF",
      "has_lookup": false
    },
    {
      "name": "Diverted2TailNum",
      "payload_name": "DIV2_TAIL_NUM",
      "response_name": "DIV2_TAIL_NUM",
      "has_lookup": false
    },
    {
      "name": "Diverted3Airport",
      "payload_name": "DIV3_AIRPORT",
      "response_name": "DIV3_AIRPORT",
      "has_lookup": false
    },
    {
      "name": "Diverted3AirportID",
      "payload_name": "DIV3_AIRPORT_ID",
      "response_name": "DIV3_AIRPORT_ID",
      "has_lookup": true,
      "lookup": "aviation.airport_id"
    },
    {
      "name": "Diverted3AirportSeqID",
      "payload_name": "DIV3_AIRPORT_SEQ_ID",
      "response_name": "DIV3_AIRPORT_SEQ_ID",
      "has_lookup": true,
      "lookup": "aviation.airport_seq_id"
    },
    {
      "name": "Diverted3WheelsOn",
      "payload_name": "DIV3_WHEELS_ON",
      "response_name": "DIV3_WHEELS_ON",
      "has_lookup": false
    },
    {
      "name": "Diverted3TotalGroundTime",
      "payload_name": "DIV3_TOTAL_GTIME",
      "response_name": "DIV3_TOTAL_GTIME",
      "has_lookup": false
    },
    {
      "name": "Diverted3LongestGroundTime",
      "payload_name": "DIV3_LONGEST_GTIME",
      "response_name": "DIV3_LONGEST_GTIME",
      "has_lookup": false
    },
    {
      "name": "Diverted3WheelsOff",
      "payload_name": "DIV3_WHEELS_OFF",
      "response_name": "DIV3_WHEELS_OFF",
      "has_lookup": false
    },
    {
      "name": "Diverted3TailNum",
      "payload_name": "DIV3_TAIL_NUM",
      "response_name": "DIV3_TAIL_NUM",
      "has_lookup": false
    },
    {
      "name": "Diverted4Airport",
      "payload_name": "DIV4_AIRPORT",
      "response_name": "DIV4_AIRPORT",
      "has_lookup": false
    },
    {
      "name": "Diverted4AirportID",
      "payload_name": "DIV4_AIRPORT_ID",
      "response_name": "DIV4_AIRPORT_ID",
      "has_lookup": true,
      "lookup": "aviation.airport_id"
    },
    {
      "name": "Diverted4AirportSeqID",
      "payload_name": "DIV4_AIRPORT_SEQ_ID",
      "response_name": "DIV4_AIRPORT_SEQ_ID",
      "has_lookup": true,
      "lookup": "aviation.airport_seq_id"
    },
    {
      "name": "Diverted4WheelsOn",
      "payload_name": "DIV4_WHEELS_ON",
      "response_name": "DIV4_WHEELS_ON",
      "has_lookup": false
    },
    {
      "name": "Diverted4TotalGroundTime",
      "payload_name": "DIV4_TOTAL_GTIME",
      "response_name": "DIV4_TOTAL_GTIME",
      "has_lookup": false
    },
    {
      "name": "Diverted4LongestGroundTime",
      "payload_name": "DIV4_LONGEST_GTIME",
      "response_name": "DIV4_LONGEST_GTIME",
      "has_lookup": false
    },
    {
      "name": "Diverted4WheelsOff",
      "payload_name": "DIV4_WHEELS_OFF",
      "response_name": "DIV4_WHEELS_OFF",
      "has_lookup": false
    },
    {
      "name": "Diverted4TailNum",
      "payload_name": "DIV4_TAIL_NUM",
      "response_name": "DIV4_TAIL_NUM",
      "has_lookup": false
    },
    {
      "name": "Diverted5Airport",
      "payload_name": "DIV5_AIRPORT",
      "response_name": "DIV5_AIRPORT",
      "has_lookup": false
    },
    {
      "name": "Diverted5AirportID",
      "payload_name": "DIV5_AIRPORT_ID",
      "response_name": "DIV5_AIRPORT_ID",
      "has_lookup": true,
      "lookup": "aviation.airport_id"
    },
    {
      "name": "Diverted5AirportSeqID",
      "payload_name": "DIV5_AIRPORT_SEQ_ID",
      "response_name": "DIV5_AIRPORT_SEQ_ID",
      "has_lookup": true,
      "lookup": "aviation.airport_seq_id"
    },
    {
      "name": "Diverted5WheelsOn",
      "payload_name": "DIV5_WHEELS_ON",
      "response_name": "DIV5_WHEELS_ON",
      "has_lookup": false
    },
    {
      "name": "Diverted5TotalGroundTime",
      "payload_name": "DIV5_TOTAL_GTIME",
      "response_name": "DIV5_TOTAL_GTIME",
      "has_lookup": false
    },
    {
      "name": "Diverted5LongestGroundTime",
      "payload_name": "DIV5_LONGEST_GTIME",
      "response_name": "DIV5_LONGEST_GTIME",
      "has_lookup": false
    },
    {
      "name": "Diverted5WheelsOff",
      "payload_name": "DIV5_WHEELS_OFF",
      "response_name": "DIV5_WHEELS_OFF",
      "has_lookup": false
    },
    {
      "name": "Diverted5TailNum",
      "payload_name": "DIV5_TAIL_NUM",
      "response_name": "DIV5_TAIL_NUM",
      "has_lookup": false
    }
  ]
}
